sklx/__init__.py
sklx/classifier.py
sklx/net.py
sklx/regressor.py
sklx/tests/__init__.py
sklx/tests/test_classifier.py
sklx/tests/test_regressor.py
sklx-0.0.9.dist-info/licenses/LICENSE
sklx-0.0.9.dist-info/METADATA
sklx-0.0.9.dist-info/WHEEL
sklx-0.0.9.dist-info/top_level.txt
sklx-0.0.9.dist-info/RECORD
