Metadata-Version: 2.4
Name: sklx
Version: 0.0.9
Summary: A scikit-learn compatible neural network library that wraps MLX.
License: BSD 3-Clause License
Keywords: sklx
Requires-Python: >=3.10
License-File: LICENSE
Requires-Dist: ansi>=0.3.7
Requires-Dist: mlx>=0.24.2
Requires-Dist: numpy>=2.0.0
Requires-Dist: scikit-learn>=1.5.1
Requires-Dist: tabulate>=0.9.0
Requires-Dist: urllib3>=2.6.3
Provides-Extra: docs
Requires-Dist: mkdocs>=1.6.1; extra == "docs"
Requires-Dist: mkdocs-material>=9.5.42; extra == "docs"
Requires-Dist: mkdocstrings[python]>=0.27.0; extra == "docs"
Dynamic: license-file
